MANIFEST.in
README.rst
setup.py
bin/prox_check
bin/prox_geo
bin/prox_task
prox/__init__.py
prox/api.py
prox/database.py
prox/prox_check.py
prox/prox_geo.py
prox/prox_task.py
prox.egg-info/PKG-INFO
prox.egg-info/SOURCES.txt
prox.egg-info/dependency_links.txt
prox.egg-info/requires.txt
prox.egg-info/top_level.txt
prox/database/GeoLite2-Country.mmdb