Metadata-Version: 1.1
Name: prox
Version: 0.0.16
Summary: The tool to check the health of proxy list
Home-page: http://github.com/lorien/prox
Author: Gregory Petukhov
Author-email: lorien@lorien.name
License: MIT
Keywords: proxy proxylist
Platform: UNKNOWN
Classifier: Programming Language :: Python
Classifier: Programming Language :: Python :: 3.4
Classifier: License :: OSI Approved :: MIT License
Classifier: Development Status :: 5 - Production/Stable
Classifier: Environment :: Console
Classifier: Intended Audience :: Developers
Classifier: Operating System :: OS Independent
Classifier: Topic :: Software Development :: Libraries :: Python Modules
Classifier: Topic :: Utilities
